innerverz_package/__init__.py
innerverz_package/deblurrer/__init__.py
innerverz_package/deblurrer/main.py
innerverz_package/deblurrer/nets.py
innerverz_package/deblurrer/test.py
innerverz_package/deep3dmm/__init__.py
innerverz_package/deep3dmm/main.py
innerverz_package/deep3dmm/nets.py
innerverz_package/face_alignment/__init__.py
innerverz_package/face_alignment/graphic_utils.py
innerverz_package/face_alignment/landmark.py
innerverz_package/face_alignment/main.py
innerverz_package/face_alignment/retina_face.py
innerverz_package/face_alignment/utils/__init__.py
innerverz_package/face_alignment/utils/face_align.py
innerverz_package/face_alignment/utils/transform.py
innerverz_package/face_color_transfer/__init__.py
innerverz_package/face_color_transfer/main.py
innerverz_package/face_color_transfer/nets.py
innerverz_package/face_color_transfer/test.py
innerverz_package/face_color_transfer/sub_nets/__init__.py
innerverz_package/face_color_transfer/sub_nets/blend_net.py
innerverz_package/face_color_transfer/sub_nets/discriminator.py
innerverz_package/face_color_transfer/sub_nets/vgg19_net.py
innerverz_package/face_color_transfer/sub_nets/warp_net.py
innerverz_package/face_color_transfer/utils/__init__.py
innerverz_package/face_color_transfer/utils/utils.py
innerverz_package/face_parser/__init__.py
innerverz_package/face_parser/main.py
innerverz_package/face_parser/model.py
innerverz_package/face_parser/resnet.py
innerverz_package/face_parser/utils/__init__.py
innerverz_package/face_parser/utils/mask_utils.py
innerverz_package/face_parser/utils/utils.py
innerverz_package/head_color_transfer/__init__.py
innerverz_package/head_color_transfer/main.py
innerverz_package/head_color_transfer/nets.py
innerverz_package/head_color_transfer/sub_nets/__init__.py
innerverz_package/head_color_transfer/sub_nets/blend_net.py
innerverz_package/head_color_transfer/sub_nets/discriminator.py
innerverz_package/head_color_transfer/sub_nets/vgg19_net.py
innerverz_package-0.0.11.dist-info/LICENSE.txt
innerverz_package-0.0.11.dist-info/METADATA
innerverz_package-0.0.11.dist-info/WHEEL
innerverz_package-0.0.11.dist-info/top_level.txt
innerverz_package-0.0.11.dist-info/RECORD
